pyapikey/__init__.py
pyapikey/core.py
pyapikey/static.py
pyapikey-0.0.13.dist-info/METADATA
pyapikey-0.0.13.dist-info/WHEEL
pyapikey-0.0.13.dist-info/licenses/LICENSE
pyapikey-0.0.13.dist-info/RECORD
