Metadata-Version: 2.4
Name: pyapikey
Version: 0.0.13
Summary: access api keys from code
Project-URL: Homepage, https://github.com/veltzer/pyapikey
Project-URL: Bug Tracker, https://github.com/veltzer/pyapikey/issues
Project-URL: Documentation, https://veltzer.github.io/pyapikey
Project-URL: Download, https://pypi.org/project/pyapikey/
Project-URL: Repository, https://github.com/veltzer/pyapikey
Author-email: Mark Veltzer <mark.veltzer@gmail.com>
Maintainer-email: Mark Veltzer <mark.veltzer@gmail.com>
License-Expression: MIT
License-File: LICENSE
Keywords: api,key,python,secret
Classifier: Development Status :: 4 - Beta
Classifier: Environment :: Console
Classifier: License :: OSI Approved :: MIT License
Classifier: Operating System :: OS Independent
Classifier: Programming Language :: Python
Classifier: Programming Language :: Python :: 3
Classifier: Programming Language :: Python :: 3 :: Only
Classifier: Programming Language :: Python :: 3.12
Classifier: Topic :: Utilities
Requires-Python: >=3.12
